{
  "version": "0.4.36",
  "flags": {},
  "shapes": [
    {
      "label": "board",
      "text": "",
      "points": [
        [
          219.4298245614035,
          257.76315789473676
        ],
        [
          644.8684210526317,
          413.02631578947364
        ],
        [
          522.938596491228,
          654.254385964912
        ],
        [
          154.5175438596491,
          523.5526315789474
        ]
      ],
      "group_id": null,
      "shape_type": "polygon",
      "flags": {}
    }
  ],
  "imagePath": "img_86.jpg",
  "imageData": null,
  "imageHeight": 1280,
  "imageWidth": 720
}