{
  "version": "0.4.36",
  "flags": {},
  "shapes": [
    {
      "label": "board",
      "text": "",
      "points": [
        [
          22.061403508771946,
          365.6578947368421
        ],
        [
          625.5701754385964,
          360.39473684210526
        ],
        [
          673.8157894736842,
          777.9385964912278
        ],
        [
          8.026315789473756,
          786.7105263157895
        ]
      ],
      "group_id": null,
      "shape_type": "polygon",
      "flags": {}
    }
  ],
  "imagePath": "img_14.jpg",
  "imageData": null,
  "imageHeight": 1280,
  "imageWidth": 720
}